my_own_package/__init__.py
first_package_Lazar_Radu-0.1.0.dist-info/METADATA
first_package_Lazar_Radu-0.1.0.dist-info/WHEEL
first_package_Lazar_Radu-0.1.0.dist-info/top_level.txt
first_package_Lazar_Radu-0.1.0.dist-info/RECORD
