Metadata-Version: 2.1
Name: first-package-Lazar-Radu
Version: 0.1.0
Summary: My_first_package
Author: Lazar Radu
Author-email: radubond@yahoo.com
